tableau_prometheus_exporter/__init__.py
tableau_prometheus_exporter/__main__.py
tableau_prometheus_exporter/main.py
tableau_prometheus_exporter/server.py
tableau_prometheus_exporter/tableau/__init__.py
tableau_prometheus_exporter/tableau/session.py
tableau_prometheus_exporter/tableau/utils.py
tableau_prometheus_exporter-0.3.2.dist-info/LICENSE.txt
tableau_prometheus_exporter-0.3.2.dist-info/METADATA
tableau_prometheus_exporter-0.3.2.dist-info/WHEEL
tableau_prometheus_exporter-0.3.2.dist-info/entry_points.txt
tableau_prometheus_exporter-0.3.2.dist-info/top_level.txt
tableau_prometheus_exporter-0.3.2.dist-info/RECORD
