Metadata-Version: 2.1
Name: tableau-prometheus-exporter
Version: 0.3.2
Summary: Tableau Server Manager Prometheus Exporter
Home-page: https://github.com/freenowtech/tableau-prometheus-exporter/
Author: sergioasantiago
Author-email: sergio.a.santiago@gmail.com
License: Apache-2.0
Project-URL: Documentation, https://github.com/freenowtech/tableau-prometheus-exporter/
Project-URL: Source, https://github.com/freenowtech/tableau-prometheus-exporter/
Platform: any
Classifier: Development Status :: 4 - Beta
Classifier: Programming Language :: Python
License-File: LICENSE.txt
Requires-Dist: requests >=2.31.0
Requires-Dist: prometheus-client ==0.17.1
Requires-Dist: urllib3 >=2.0.4
Requires-Dist: pyyaml >=6.0.1
Requires-Dist: importlib-metadata ; python_version < "3.8"
Provides-Extra: testing
Requires-Dist: setuptools ; extra == 'testing'
Requires-Dist: pytest ; extra == 'testing'
Requires-Dist: pytest-cov ; extra == 'testing'
Requires-Dist: pytest-mock ; extra == 'testing'
